deep_animator/__init__.py
deep_animator/_nbdev.py
deep_animator/cli.py
deep_animator/utils.py
deep_animator/modules/__init__.py
deep_animator/modules/dense_motion.py
deep_animator/modules/generator.py
deep_animator/modules/kp_detector.py
deep_animator/modules/utils.py
deep_animator/sync_batchnorm/__init__.py
deep_animator/sync_batchnorm/batchnorm.py
deep_animator/sync_batchnorm/comm.py
deep_animator/sync_batchnorm/replicate.py
deep_animator-0.1.1.dist-info/LICENSE
deep_animator-0.1.1.dist-info/METADATA
deep_animator-0.1.1.dist-info/WHEEL
deep_animator-0.1.1.dist-info/entry_points.txt
deep_animator-0.1.1.dist-info/top_level.txt
deep_animator-0.1.1.dist-info/RECORD
