Metadata-Version: 2.1
Name: deep-animator
Version: 0.1.1
Summary: Image animation given a driving video sequence and a source image.
Home-page: https://github.com/dpoulopoulos/deep_animator
Author: Dimitris Poulopoulos
Author-email: dimitris.a.poulopoulos@gmail.com
License: Apache Software License 2.0
Keywords: deep fake,deep learning,image animation,generative models
Platform: UNKNOWN
Classifier: Development Status :: 3 - Alpha
Classifier: Intended Audience :: Developers
Classifier: License :: OSI Approved :: Apache Software License
Classifier: Natural Language :: English
Classifier: Programming Language :: Python :: 3.6
Classifier: Programming Language :: Python :: 3.7
Classifier: Programming Language :: Python :: 3.8
Requires-Python: >=3.6
Requires-Dist: torch (>=1.3.0)
Requires-Dist: torchvision (>=0.2.1)
Requires-Dist: tqdm
Requires-Dist: imageio (==2.3.0)
Requires-Dist: matplotlib (==2.2.2)
Requires-Dist: numpy (==1.15.0)
Requires-Dist: pandas (==0.23.4)
Requires-Dist: Pillow (==5.2.0)
Requires-Dist: scikit-image (==0.14.0)
Requires-Dist: scikit-learn (==0.19.2)
Requires-Dist: scipy (==1.1.0)
Requires-Dist: fire
Requires-Dist: ffmpeg
